floodmodeller_api/__init__.py
floodmodeller_api/_base.py
floodmodeller_api/backup.py
floodmodeller_api/dat.py
floodmodeller_api/diff.py
floodmodeller_api/ied.py
floodmodeller_api/ief.py
floodmodeller_api/ief_flags.py
floodmodeller_api/inp.py
floodmodeller_api/mapping.py
floodmodeller_api/to_from_json.py
floodmodeller_api/tool.py
floodmodeller_api/util.py
floodmodeller_api/version.py
floodmodeller_api/xml2d.py
floodmodeller_api/xml2d_template.py
floodmodeller_api/xsd_backup.xml
floodmodeller_api/zz.py
floodmodeller_api/hydrology_plus/__init__.py
floodmodeller_api/hydrology_plus/helper.py
floodmodeller_api/hydrology_plus/hydrology_plus_export.py
floodmodeller_api/libs/libifcoremd.dll
floodmodeller_api/libs/libifcoremt.so.5
floodmodeller_api/libs/libifport.so.5
floodmodeller_api/libs/libimf.so
floodmodeller_api/libs/libintlc.so.5
floodmodeller_api/libs/libmmd.dll
floodmodeller_api/libs/libsvml.so
floodmodeller_api/libs/libzzn_read.so
floodmodeller_api/libs/zzn_read.dll
floodmodeller_api/logs/__init__.py
floodmodeller_api/logs/lf.py
floodmodeller_api/logs/lf_helpers.py
floodmodeller_api/logs/lf_params.py
floodmodeller_api/test/__init__.py
floodmodeller_api/test/conftest.py
floodmodeller_api/test/test_backup.py
floodmodeller_api/test/test_conveyance.py
floodmodeller_api/test/test_dat.py
floodmodeller_api/test/test_flowtimeprofile.py
floodmodeller_api/test/test_fmfile.py
floodmodeller_api/test/test_gxy.py
floodmodeller_api/test/test_hydrology_plus_export.py
floodmodeller_api/test/test_ied.py
floodmodeller_api/test/test_ief.py
floodmodeller_api/test/test_inp.py
floodmodeller_api/test/test_integrated_bridge.py
floodmodeller_api/test/test_json.py
floodmodeller_api/test/test_logs_lf.py
floodmodeller_api/test/test_read_file.py
floodmodeller_api/test/test_river.py
floodmodeller_api/test/test_sluice.py
floodmodeller_api/test/test_tool.py
floodmodeller_api/test/test_toolbox_structure_log.py
floodmodeller_api/test/test_unit.py
floodmodeller_api/test/test_xml2d.py
floodmodeller_api-0.5.5.post1.dist-info/licenses/LICENSE.txt
floodmodeller_api-0.5.5.post1.dist-info/METADATA
floodmodeller_api-0.5.5.post1.dist-info/WHEEL
floodmodeller_api-0.5.5.post1.dist-info/entry_points.txt
floodmodeller_api-0.5.5.post1.dist-info/top_level.txt
floodmodeller_api-0.5.5.post1.dist-info/RECORD
