Metadata-Version: 2.4
Name: floodmodeller_api
Version: 0.5.5.post1
Summary: Extends the functionality of Flood Modeller to python users
Author: Jacobs
Author-email: joe.pierce@jacobs.com
License: GNU General Public License V3. Copyright (C) 2025 Jacobs U.K. Limited.
Project-URL: API Documentation, https://api.floodmodeller.com/api/
Project-URL: Flood Modeller Homepage, https://www.floodmodeller.com/
Project-URL: Contact & Support, https://www.floodmodeller.com/contact
License-File: LICENSE.txt
Requires-Dist: pandas<3,>1
Requires-Dist: lxml==5.*
Requires-Dist: tqdm==4.*
Requires-Dist: pytest<8,>4
Requires-Dist: pytest-mock==3.*
Requires-Dist: shapely==2.*
Requires-Dist: scipy==1.*
Requires-Dist: freezegun==1.*
Requires-Dist: requests>2.23
Dynamic: author
Dynamic: author-email
Dynamic: description
Dynamic: description-content-type
Dynamic: license
Dynamic: license-file
Dynamic: project-url
Dynamic: requires-dist
Dynamic: summary
